Lws_Test/__init__.py
Lws_Test/object_detection/__init__.py
Lws_Test/object_detection/analysis/__init__.py
Lws_Test/object_detection/config/__init__.py
Lws_Test/object_detection/models/__init__.py
Lws_Test/object_detection/post_processing/__init__.py
Lws_Test/object_detection/pre_processing/__init__.py
Lws_Test/object_detection/utils/__init__.py
lws_test-1.0.5.dist-info/METADATA
lws_test-1.0.5.dist-info/WHEEL
lws_test-1.0.5.dist-info/top_level.txt
lws_test-1.0.5.dist-info/RECORD
