Metadata-Version: 2.4
Name: Lws_Test
Version: 1.0.5
Summary: Lws_Test
License: Apache License 2.0
Requires-Dist: opencv-python==4.10.0.84
Requires-Dist: shapely==2.0.6
Requires-Dist: psutil
Dynamic: license
Dynamic: requires-dist
Dynamic: summary
